pytest_enabler/__init__.py
pytest_enabler/default.toml
pytest_enabler/py.typed
pytest_enabler-3.3.0.dist-info/LICENSE
pytest_enabler-3.3.0.dist-info/METADATA
pytest_enabler-3.3.0.dist-info/WHEEL
pytest_enabler-3.3.0.dist-info/entry_points.txt
pytest_enabler-3.3.0.dist-info/top_level.txt
pytest_enabler-3.3.0.dist-info/RECORD
